LICENSE.txt
MANIFEST.in
README.md
pyproject.toml
setup.cfg
setup.py
data/data_file
src/MLUtilities/Day_diff.py
src/MLUtilities/__init__.py
src/MLUtilities/binary_model_evaluator.py
src/MLUtilities/date_feat.py
src/MLUtilities/lift_boolean.py
src/MLUtilities/lift_cat.py
src/MLUtilities/multicolumnlabelencoder.py
src/MLUtilities/package_data.dat
src/MLUtilities/percent_missing.py
src/MLUtilities/plot_correlation.py
src/MLUtilities/plotconfusionmatrix.py
src/MLUtilities/remove_correlation.py
src/MLUtilities/remove_zero_variance.py
src/MLUtilities/replacemissing.py
src/MLUtilities.egg-info/PKG-INFO
src/MLUtilities.egg-info/SOURCES.txt
src/MLUtilities.egg-info/dependency_links.txt
src/MLUtilities.egg-info/requires.txt
src/MLUtilities.egg-info/top_level.txt
src/MLUtilities/tests/__init__.py