Metadata-Version: 2.1
Name: MLUtilities
Version: 1.0.0
Summary: A collection of tools for machine learning preprocessing
Home-page: https://github.com/NanaAkwasiAbayieBoateng/MLUtilies
Author: Nana  Boateng
Author-email: unltd148@yahoo.co.uk
License: UNKNOWN
Project-URL: Bug Reports, https://github.com/NanaAkwasiAbayieBoateng/MLUtilies/issues
Project-URL: Funding, http://restanalytics.com/
Project-URL: Say Thanks!, http://restanalytics.com/
Project-URL: Source, https://github.com/NanaAkwasiAbayieBoateng/MLUtilies
Keywords: machine learning,date feature engineering,
Platform: UNKNOWN
Classifier: Development Status :: 3 - Alpha
Classifier: Operating System :: Microsoft :: Windows :: Windows 10
Classifier: Topic :: Software Development :: Build Tools
Classifier: License :: OSI Approved :: MIT License
Classifier: Programming Language :: Python :: 3
Classifier: Programming Language :: Python :: 3.6
Classifier: Programming Language :: Python :: 3.7
Classifier: Programming Language :: Python :: 3.8
Classifier: Programming Language :: Python :: 3.9
Classifier: Programming Language :: Python :: 3 :: Only
Requires-Python: >=3.6
